pycdek3/__init__.py
pycdek3/client.py
pycdek3-0.2.0.dist-info/LICENSE
pycdek3-0.2.0.dist-info/METADATA
pycdek3-0.2.0.dist-info/WHEEL
pycdek3-0.2.0.dist-info/top_level.txt
pycdek3-0.2.0.dist-info/RECORD
