Metadata-Version: 2.1
Name: pycdek3
Version: 0.2.0
Summary: Python3 client for CDEK API
Home-page: https://github.com/kpodranyuk/pycdek3
Author: Ekaterina Podranyuk
Author-email: katherineswork44@gmail.com
License: MIT
Platform: UNKNOWN
Classifier: Development Status :: 4 - Beta
Classifier: Environment :: Web Environment
Classifier: Intended Audience :: Developers
Classifier: License :: OSI Approved :: MIT License
Classifier: Operating System :: OS Independent
Classifier: Programming Language :: Python :: 3
Classifier: Topic :: Software Development :: Libraries :: Python Modules
Requires-Python: >=3.4
